odoo/addons/stock_quant_reservation_info_mrp/README.rst
odoo/addons/stock_quant_reservation_info_mrp/__init__.py
odoo/addons/stock_quant_reservation_info_mrp/__manifest__.py
odoo/addons/stock_quant_reservation_info_mrp/i18n/it.po
odoo/addons/stock_quant_reservation_info_mrp/i18n/stock_quant_reservation_info_mrp.pot
odoo/addons/stock_quant_reservation_info_mrp/models/__init__.py
odoo/addons/stock_quant_reservation_info_mrp/models/stock_move_line.py
odoo/addons/stock_quant_reservation_info_mrp/readme/CONTRIBUTORS.md
odoo/addons/stock_quant_reservation_info_mrp/readme/DESCRIPTION.md
odoo/addons/stock_quant_reservation_info_mrp/readme/USAGE.md
odoo/addons/stock_quant_reservation_info_mrp/static/description/icon.png
odoo/addons/stock_quant_reservation_info_mrp/static/description/index.html
odoo/addons/stock_quant_reservation_info_mrp/views/stock_move_line.xml
odoo_addon_stock_quant_reservation_info_mrp-18.0.1.0.0.2.dist-info/METADATA
odoo_addon_stock_quant_reservation_info_mrp-18.0.1.0.0.2.dist-info/WHEEL
odoo_addon_stock_quant_reservation_info_mrp-18.0.1.0.0.2.dist-info/top_level.txt
odoo_addon_stock_quant_reservation_info_mrp-18.0.1.0.0.2.dist-info/RECORD
