Metadata-Version: 2.1
Name: odoo-addon-stock_quant_reservation_info_mrp
Version: 18.0.1.0.0.2
Requires-Python: >=3.10
Requires-Dist: odoo-addon-stock_quant_reservation_info==18.0.*
Requires-Dist: odoo==18.0.*
Summary: Allows to see the manufacturing order related to the reserved info of Products
Home-page: https://github.com/OCA/stock-logistics-warehouse
License: AGPL-3
Author: ForgeFlow, Odoo Community Association (OCA)
Author-email: support@odoo-community.org
Classifier: Programming Language :: Python
Classifier: Framework :: Odoo
Classifier: Framework :: Odoo :: 18.0
Classifier: License :: OSI Approved :: GNU Affero General Public License v3
